src/ALU_flags.v
/*
Author: Nishaanth Sai Vinodh Kumar
Project: 8-Bit ALU With Flags
Language: Verilog HDL
*/


module ALU_flags (
    input [7:0] a,      // First 8-bit operand
    input [7:0] b,      // Second 8-bit operand
    input [3:0] sel,    // Operation select signal
    output reg [7:0] out,// Output
    output reg zero,carry,overflow,negative // flags
);

// 8-Bit Arithmetic Logic Unit (ALU)
// ---------------------------------
// Operation Codes:
//
// 0001 : Addition       (a + b)
// 0010 : Subtraction    (a - b)
// 0011 : Bitwise AND    (a & b)
// 0100 : Bitwise OR     (a | b)
// 0101 : Bitwise XOR    (a ^ b)
// 0111 : Bitwise NOT A  (~a)
// 1000 : Bitwise NOT B  (~b)
// 1001 : Shift Right    (a >> b)
// 1010 : Shift Left     (a << b)
// 1011 : Compare        (a < b)
//
// Any undefined outputs 0
localparam ADD = 4'b0001;
localparam SUB = 4'b0010;
localparam AND = 4'b0011;
localparam OR = 4'b0100;
localparam XOR = 4'b0101;
localparam NOT_A = 4'b0111;
localparam NOT_B = 4'b1000;
localparam SHIFT_RIGHT = 4'b1001;
localparam SHIFT_LEFT = 4'b1010;
localparam COMPARISON = 4'b1011;

reg[8:0] a_out; // ALU actual output

always @(*) begin
    carry = 0;
    overflow = 0; 
    zero = 0;
    negative = 0;

    // Select operation based on sel input
    case(sel)

        ADD: 
        begin
            a_out = {1'b0, a} + {1'b0, b}; 

            carry = a_out[8];
            
            if (((a[7] ==  b[7]) ) && (a_out[7] != a[7]))
                overflow = 1; 
            
            out = a_out[7:0];
        end

        SUB:         
        begin 
            a_out = {1'b0, a} - {1'b0, b};     
            
            carry = ~a_out[8];
           
            if (((a[7] != b[7])) && (a_out[7] != a[7]))
                overflow = 1; 
                     
            out = a_out[7:0];
        end

        AND:         out = a & b;      // Bitwise AND

        OR:          out = a | b;      // Bitwise OR

        XOR:         out = a ^ b;      // Bitwise XOR

        NOT_A:       out = ~a;         // Bitwise NOT of A

        NOT_B:       out = ~b;         // Bitwise NOT of B

        SHIFT_RIGHT: out = a >> b;     // Logical right shift by B positions

        SHIFT_LEFT: out = a << b;     // Logical left shift by B positions

        COMPARISON: out = (a < b) ? 8'b00000001 : 8'b00000000; // Outputs 1 if A < B, otherwise 0

        default: out = 0;          // Default output for undefined opcodes
        



    endcase

        negative = out[7];
        zero = (out == 8'b00000000);
   
     
end


endmodule

tb/ALU_flags_tb.v
module ALU_flags_tb ;

 reg [7:0] a; 
 reg [7:0] b;
 reg [3:0] sel;
 wire [7:0] out;
 wire zero,carry,overflow,negative;

ALU_flags DUT (.a(a),
               .b(b),
               .sel(sel),
               .out(out),
               .zero(zero),
               .carry(carry),
               .overflow(overflow),
               .negative(negative));

initial begin

    $monitor ($time, "A = %d , B = %d, sel = %d, out = %d, zero = %d, carry = %d, overflow = %d, negative = %d ", a,b,sel,out,zero,carry,overflow,negative);

    // Create waveform dump file for GTKWave
        $dumpfile("flag_result.vcd");

        // Dump all signals in the testbench hierarchy
        $dumpvars(0, ALU_flags_tb);
    #5

       /* Addition (0001): Expected outputs given inputs

       | A   | B   | Expected Out | C | O | Z | N |
       --------------------------------------------
       | 3   | 2   | 5            | 0 | 0 | 0 | 0 |
       | 15  | 1   | 16           | 0 | 0 | 0 | 0 |
       | 255 | 1   | 0            | 1 | 0 | 1 | 0 |
       | 127 | 1   | 128          | 0 | 1 | 0 | 1 |
       | 128 | 255 | 127          | 1 | 1 | 0 | 0 |
    */
        a =  3 ; b = 2; sel = 1; #5
        a =  15 ; b = 1; sel = 1; #5
        a =  255 ; b = 1; sel = 1; #5
        a = 127 ; b = 1; sel = 1; #5
        a =  128 ; b = 255; sel = 1; #5

        /* SUB(0010): Expected outputs given inputs
        | A          | B        | Expected Out | C (borrow) | O | Z | N |
        ------------------------------------------------------------------
        | 6          | 3        | 3            | 0          | 0 | 0 | 0 |
        | 5          | 5        | 0            | 0          | 0 | 1 | 0 |
        | 2          | 4        | 254          | 1          | 0 | 0 | 1 |
        | 127        | 255 (-1) | 128          | 1          | 1 | 0 | 1 |
        | 128 (-128) | 1        | 127          | 0          | 1 | 0 | 0 |
        */
         a =  6 ; b = 3; sel = 2; #5
         a =  5 ; b = 5; sel = 2; #5
         a =  2 ; b = 4; sel = 2; #5
         a =  127 ; b = 255; sel = 2; #5
         a =  128 ; b = 1; sel = 2; #5

         /* AND (0011): Expected outputs given inputs
            | A        | B        | Expected Out | 
            | -------- | -------- | ------------ |
            | 11001100 | 10101010 | 10001000     |
            | 11111111 | 00000000 | 00000000     |
                          
        */
             a = 8'b11001100 ; b = 8'b10101010; sel = 3; #5
             a = 8'b11111111 ; b = 8'b00000000; sel = 3; #5



        /* OR (0100): Expected outputs given inputs
            | A        | B        | Expected Out |
            | -------- | -------- | ------------ |
            | 11001100 | 10101010 | 11101110     |
            | 00000000 | 00000000 | 00000000     |
                         
        */
            a = 8'b11001100 ; b = 8'b10101010; sel = 4; #5
            a = 8'b00000000 ; b = 8'b00000000; sel = 4; #5


        /* XOR (0101): Expected outputs given inputs
            | A        | B        | Expected Out |
            | -------- | -------- | ------------ |
            | 11001100 | 10101010 | 01100110     |
            | 11111111 | 11111111 | 00000000     |
        */
            a = 8'b11001100 ; b = 8'b10101010; sel = 5; #5
            a = 8'b11111111 ; b = 8'b11111111; sel = 5; #5
        
        /* NOT A(0111): Expected outputs given inputs
            | A        | Expected Out |
            | -------- | ------------ |
            | 10101010 | 01010101     |
            | 11111111 | 00000000     |
        */
            a = 8'b10101010 ; sel = 7; #5
            a = 8'b11111111 ; sel = 7; #5

        /* NOT B(1000):Expected outputs given inputs
            | B        | Expected Out |
            | -------- | ------------ |
            | 11001100 | 00110011     |
            | 11111111 | 00000000     |
        */

            b = 8'b11001100 ; sel = 8; #5
            b = 8'b11111111 ; sel = 8; #5

        /* Shift Right (1001): Expected outputs given inputs
            | A        | B | Expected Out |
            | -------- | - | ------------ |
            | 10000000 | 1 | 01000000     |
            | 10000000 | 4 | 00001000     |
            | 11111111 | 8 | 00000000     |
        */
             a = 8'b10000000 ; b = 8'b00000001; sel = 9; #5
             a = 8'b10000000 ; b = 8'b00000100; sel = 9; #5
             a = 8'b11111111 ; b = 8'b00001000; sel = 9; #5

        /* Shift Left (1010): Expected outputs given inputs
             | A        | B        | Expected Out |
             | -------- | -------- | ------------ |
             | 00000001 | 00000100 | 00010000     |
             | 10000000 | 00000000 | 10000000     |
             | 00000001 | 10000000 | 00000000     |
        */
             a = 8'b00000001 ; b = 8'b00000100; sel = 10; #5
             a = 8'b10000000 ; b = 8'b00000000; sel = 10; #5
             a = 8'b00000001 ; b = 8'b10000000; sel = 10; #5
        
        
         /* Comparison(1011): Expected outputs given inputs
             | A | B | Expected Out |
             | - | - | ------------ |
             | 3 | 5 | 1            |
             | 8 | 2 | 0            |
             | 4 | 4 | 0            |
        */
            a =  3 ; b = 5; sel = 11; #5
            a =  8 ; b = 2; sel = 11; #5
            a =  4 ; b = 4; sel = 11; #5

        #10
        $finish;

end
endmodule

flag_result.vcd
$date
	Thu Jun 18 22:43:04 2026
$end
$version
	Icarus Verilog
$end
$timescale
	1s
$end
$scope module ALU_flags_tb $end
$var wire 1 ! zero $end
$var wire 1 " overflow $end
$var wire 8 # out [7:0] $end
$var wire 1 $ negative $end
$var wire 1 % carry $end
$var reg 8 & a [7:0] $end
$var reg 8 ' b [7:0] $end
$var reg 4 ( sel [3:0] $end
$scope module DUT $end
$var wire 8 ) a [7:0] $end
$var wire 8 * b [7:0] $end
$var wire 4 + sel [3:0] $end
$var parameter 4 , ADD $end
$var parameter 4 - AND $end
$var parameter 4 . COMPARISON $end
$var parameter 4 / NOT_A $end
$var parameter 4 0 NOT_B $end
$var parameter 4 1 OR $end
$var parameter 4 2 SHIFT_LEFT $end
$var parameter 4 3 SHIFT_RIGHT $end
$var parameter 4 4 SUB $end
$var parameter 4 5 XOR $end
$var reg 9 6 a_out [8:0] $end
$var reg 1 % carry $end
$var reg 1 $ negative $end
$var reg 8 7 out [7:0] $end
$var reg 1 " overflow $end
$var reg 1 ! zero $end
$upscope $end
$upscope $end
$enddefinitions $end
$comment Show the parameter values. $end
$dumpall
b101 5
b10 4
b1001 3
b1010 2
b100 1
b1000 0
b111 /
b1011 .
b11 -
b1 ,
$end
#0
$dumpvars
bx 7
bx 6
bx +
bx *
bx )
bx (
bx '
bx &
x%
x$
bx #
x"
x!
$end
#5
b101 #
b101 7
b101 6
0$
0!
0"
0%
b1 (
b1 +
b10 '
b10 *
b11 &
b11 )
#10
b10000 #
b10000 7
b10000 6
b1 '
b1 *
b1111 &
b1111 )
#15
1!
b0 #
b0 7
1%
b100000000 6
b11111111 &
b11111111 )
#20
1$
b10000000 #
b10000000 7
1"
b10000000 6
0!
0%
b1111111 &
b1111111 )
#25
b1111111 #
b1111111 7
1%
b101111111 6
0$
1"
b11111111 '
b11111111 *
b10000000 &
b10000000 )
#30
b11 #
b11 7
b11 6
0"
1%
b10 (
b10 +
b11 '
b11 *
b110 &
b110 )
#35
1!
b0 #
b0 7
b0 6
1%
b101 '
b101 *
b101 &
b101 )
#40
1$
b11111110 #
b11111110 7
b111111110 6
0!
0%
b100 '
b100 *
b10 &
b10 )
#45
b10000000 #
b10000000 7
1"
b110000000 6
1$
b11111111 '
b11111111 *
b1111111 &
b1111111 )
#50
b1111111 #
b1111111 7
1%
b1111111 6
0$
1"
b1 '
b1 *
b10000000 &
b10000000 )
#55
1$
b10001000 #
b10001000 7
0"
0%
b11 (
b11 +
b10101010 '
b10101010 *
b11001100 &
b11001100 )
#60
1!
b0 #
b0 7
0$
b0 '
b0 *
b11111111 &
b11111111 )
#65
1$
b11101110 #
b11101110 7
0!
b100 (
b100 +
b10101010 '
b10101010 *
b11001100 &
b11001100 )
#70
1!
b0 #
b0 7
0$
b0 '
b0 *
b0 &
b0 )
#75
b1100110 #
b1100110 7
0!
b101 (
b101 +
b10101010 '
b10101010 *
b11001100 &
b11001100 )
#80
1!
b0 #
b0 7
b11111111 '
b11111111 *
b11111111 &
b11111111 )
#85
b1010101 #
b1010101 7
0!
b111 (
b111 +
b10101010 &
b10101010 )
#90
1!
b0 #
b0 7
b11111111 &
b11111111 )
#95
b110011 #
b110011 7
0!
b1000 (
b1000 +
b11001100 '
b11001100 *
#100
1!
b0 #
b0 7
b11111111 '
b11111111 *
#105
b1000000 #
b1000000 7
0!
b1001 (
b1001 +
b1 '
b1 *
b10000000 &
b10000000 )
#110
b1000 #
b1000 7
b100 '
b100 *
#115
1!
b0 #
b0 7
b1000 '
b1000 *
b11111111 &
b11111111 )
#120
b10000 #
b10000 7
0!
b1010 (
b1010 +
b100 '
b100 *
b1 &
b1 )
#125
1$
b10000000 #
b10000000 7
b0 '
b0 *
b10000000 &
b10000000 )
#130
1!
b0 #
b0 7
0$
b10000000 '
b10000000 *
b1 &
b1 )
#135
b1 #
b1 7
0!
b1011 (
b1011 +
b101 '
b101 *
b11 &
b11 )
#140
1!
b0 #
b0 7
b10 '
b10 *
b1000 &
b1000 )
#145
1!
b100 '
b100 *
b100 &
b100 )
